screen_brightness_control/__init__.py
screen_brightness_control/__main__.py
screen_brightness_control/_debug.py
screen_brightness_control/_version.py
screen_brightness_control/config.py
screen_brightness_control/exceptions.py
screen_brightness_control/helpers.py
screen_brightness_control/linux.py
screen_brightness_control/types.py
screen_brightness_control/windows.py
screen_brightness_control-0.25.0.dist-info/licenses/LICENSE
screen_brightness_control-0.25.0.dist-info/METADATA
screen_brightness_control-0.25.0.dist-info/WHEEL
screen_brightness_control-0.25.0.dist-info/top_level.txt
screen_brightness_control-0.25.0.dist-info/RECORD
