Metadata-Version: 2.4
Name: screen_brightness_control
Version: 0.25.0
Summary: A Python tool for controlling the brightness of your monitor
Author-email: Crozzers <captaincrozzers@gmail.com>
License: MIT
Project-URL: Source, https://github.com/Crozzers/screen_brightness_control
Project-URL: Documentation, https://crozzers.github.io/screen_brightness_control
Project-URL: Issues, https://github.com/Crozzers/screen_brightness_control/issues
Classifier: Development Status :: 4 - Beta
Classifier: License :: OSI Approved :: MIT License
Classifier: Operating System :: Microsoft :: Windows :: Windows 10
Classifier: Operating System :: Microsoft :: Windows :: Windows 11
Classifier: Operating System :: POSIX :: Linux
Classifier: Programming Language :: Python :: 3 :: Only
Requires-Python: >=3.8
License-File: LICENSE
Requires-Dist: wmi; platform_system == "Windows"
Requires-Dist: pywin32; platform_system == "Windows"
Requires-Dist: pypiwin32; platform_system == "Windows"
Provides-Extra: dist
Requires-Dist: build; extra == "dist"
Requires-Dist: setuptools; extra == "dist"
Requires-Dist: wheel; extra == "dist"
Requires-Dist: twine; extra == "dist"
Provides-Extra: dev
Requires-Dist: mypy; extra == "dev"
Requires-Dist: types-pywin32; platform_system == "Windows" and extra == "dev"
Requires-Dist: pytest; extra == "dev"
Requires-Dist: pytest-mock; extra == "dev"
Requires-Dist: pytest-subtests; extra == "dev"
Requires-Dist: ruff; extra == "dev"
Requires-Dist: string-fixer>=0.5.0; extra == "dev"
Provides-Extra: docs
Requires-Dist: jsmin; extra == "docs"
Requires-Dist: packaging; extra == "docs"
Requires-Dist: pdoc>=14.1.0; extra == "docs"
Provides-Extra: all
Requires-Dist: screen_brightness_control[dev,dist,docs]; extra == "all"
Dynamic: license-file
